simple_mac.py
simple_mac-0.0.1.dist-info/METADATA
simple_mac-0.0.1.dist-info/WHEEL
simple_mac-0.0.1.dist-info/top_level.txt
simple_mac-0.0.1.dist-info/RECORD
