Metadata-Version: 2.1
Name: simple-mac
Version: 0.0.1
Summary: An educational, non-secure MAC implementation using simple XOR.
Author: Harshil Bhatnagar
Author-email: harshilbhatnagar97@gmail.com
Classifier: Programming Language :: Python :: 3
Classifier: License :: OSI Approved :: MIT License
Classifier: Operating System :: OS Independent
Classifier: Development Status :: 3 - Alpha
Classifier: Topic :: Education
Requires-Python: >=3.6
